{
	"headline" : "Südeuropa Level 2",
	"bg" : "gfx/big/suedeuropa/SuedEuropa_mit_Grenzen.png",
	"bgx" : "150",
	"bgy" : "-380",
	"scroll": "true",
	"scrollLeft"  : "150",
	"scrollRight" : "250",
	"script": [
		"Bewege die dich mit den Pfeiltasten nach rechts und links auf der Karte, um weit entfernte Länder zu erreichen",
		"Genauso wie du es mit den Ländern Westeuropas gemacht hast, versuchst du es jetzt mit den Ländern aus Südeuropa. Bewege die dich mit den Pfeiltasten nach rechts und links auf der Karte, um weit entfernte Länder zu erreichen."
	],
	"ende1": "Puh, der Abschnitt war wirklich schwierig. Mal schauen welche unbekannten Länder wir noch entdecken werden.",
	"count" : "15",
	"images" : [
		"gfx/big/suedeuropa/Suedeuropa-0000.png",
		"gfx/big/suedeuropa/Suedeuropa-0001.png",
		"gfx/big/suedeuropa/Suedeuropa-0100.png",
		"gfx/big/suedeuropa/Suedeuropa-0101.png",
		"gfx/big/suedeuropa/Suedeuropa-1000.png",
		"gfx/big/suedeuropa/Suedeuropa-1001.png",
		"gfx/big/suedeuropa/Suedeuropa-1100.png",
		"gfx/big/suedeuropa/Suedeuropa-1101.png",
		"gfx/little/suedeuropa/flaggen/ALB.png",
		"gfx/little/suedeuropa/flaggen/BOSHER.png",
		"gfx/little/suedeuropa/flaggen/BUL.png",
		"gfx/little/suedeuropa/flaggen/CRO.png",
		"gfx/little/suedeuropa/flaggen/CYP.png",
		"gfx/little/suedeuropa/flaggen/GRE.png",
		"gfx/little/suedeuropa/flaggen/ITA.png",

		"gfx/little/suedeuropa/flaggen/MAC.png",

		"gfx/little/suedeuropa/flaggen/Portugal.png",
		"gfx/little/suedeuropa/flaggen/SER.png",
		"gfx/little/suedeuropa/flaggen/SLOVENIA.png",
		"gfx/little/suedeuropa/flaggen/Spanien.png",
		"gfx/little/suedeuropa/flaggen/TUR.png"
	],

		"puzzle" : [
		{
			"id": "0" , 
			"part": "gfx/little/suedeuropa/flaggen/ALB.png",
			"hitshape" : { "x" : "850", "y" : "400", "w" : "10" },
			"position": { "x" : "795", "y" : "275" },
			"country" : "Albanien",
			"mp3": ""
			
		},
		{
			"id": "1" , 
			"part": "gfx/little/suedeuropa/flaggen/BOSHER.png",
			"hitshape" : { "x" : "780", "y" : "320", "w" : "10" },
			"position": { "x" : "725", "y" : "195" },
			"country" : "Bosnien und Herzegowina",
			"mp3": ""
			
		},
		{
			"id": "2" , 
			"part": "gfx/little/suedeuropa/flaggen/BUL.png",
			"hitshape" : { "x" : "970", "y" : "350", "w" : "10"},
			"position": { "x" : "915", "y" : "235" },
			"country" : "Bulgarien",
			"mp3": ""

		},
		{
			"id": "3" , 
			"part": "gfx/little/suedeuropa/flaggen/CRO.png",
			"hitshape" : { "x" : "740", "y" : "300", "w" : "10" },
			"position": { "x" : "685", "y" : "175" },
			"country" : "Kroatien"
			
		},
		{
			"id": "4" , 
			"part": "gfx/little/suedeuropa/flaggen/CYP.png",
			"hitshape" : { "x" : "1185", "y" : "520", "w" : "10" },
			"position": { "x" : "1130", "y" : "395" },
			"country" : "Zypern",
			"mp3": ""
			
		},
		{
			"id": "5" , 
			"part": "gfx/little/suedeuropa/flaggen/GRE.png",
			"hitshape" : { "x" : "900", "y" : "470", "w" : "10" },
			"position": { "x" : "845", "y" : "345" },
			"country" : "Griechenland",
			"mp3": ""
			
		},
		{
			"id": "6" , 
			"part": "gfx/little/suedeuropa/flaggen/ITA.png",
			"hitshape" : { "x" : "680", "y" : "390", "w" : "10" },
			"position": { "x" : "625", "y" : "265" },
			"country" : "Italien",
			"mp3": ""
		},
		{
			"id": "7" , 
			"part": "gfx/little/suedeuropa/flaggen/KOS.png",
			"hitshape" : { "x" : "875", "y" : "360", "w" : "10" },
			"position": { "x" : "820", "y" : "235" },
			"country" : "Kosovo",
			"mp3": ""
			
		},
		{
			"id": "8" , 
			"part": "gfx/little/suedeuropa/flaggen/MAC.png",
			"hitshape" : { "x" : "900", "y" : "400", "w" : "10"},
			"position": { "x" : "845", "y" : "275" },
			"country" : "Mazedonien",
			"mp3": ""
			
		},
		{
			"id": "9" , 
			"part": "gfx/little/suedeuropa/flaggen/MON.png",
			"hitshape" : { "x" : "830", "y" : "360", "w" : "10" },
			"position": { "x" : "775", "y" : "235" },
			"country" : "Montenegro",
			"mp3": ""
			
		},
		{
			"id": "10" , 
			"part": "gfx/little/suedeuropa/flaggen/Portugal.png",
			"hitshape" : { "x" : "200", "y" : "390", "w" : "10" },
			"position": { "x" : "145", "y" : "265" },
			"country" : "Portugal",
			"mp3": ""
			
		},
		{
			"id": "11" , 
			"part": "gfx/little/suedeuropa/flaggen/SER.png",
			"hitshape" : { "x" : "870", "y" : "300", "w" : "10"},
			"position": { "x" : "815", "y" : "175" },
			"country" : "Serbien",
			"mp3": ""
			
		},
		{
			"id": "12" , 
			"part": "gfx/little/suedeuropa/flaggen/SLOVENIA.png",
			"hitshape" : { "x" : "730", "y" : "275", "w" : "10" },
			"position": { "x" : "675", "y" : "150" },
			"country" : "Slowenien",
			"mp3": ""
			
		},
		{
			"id": "13" , 
			"part": "gfx/little/suedeuropa/flaggen/Spanien.png",
			"hitshape" : { "x" : "300", "y" : "430", "w" : "10" },
			"position": { "x" : "245", "y" : "305" },
			"country" : "Spanien",
			"mp3": ""
			
		},
		{
			"id": "14" , 
			"part": "gfx/little/suedeuropa/flaggen/TUR.png",
			"hitshape" : { "x" : "1080", "y" : "450", "w" : "10" },
			"position": { "x" : "1025", "y" : "325" },
			"country" : "Türkei",
			"mp3": ""
			
		}
	]
}